README.md
setup.py
NM53/__init__.py
NM53.egg-info/PKG-INFO
NM53.egg-info/SOURCES.txt
NM53.egg-info/dependency_links.txt
NM53.egg-info/entry_points.txt
NM53.egg-info/not-zip-safe
NM53.egg-info/requires.txt
NM53.egg-info/top_level.txt