Metadata-Version: 1.0
Name: NM53
Version: 2019.2.25.1354
Summary: create and update backups of GitHub repositories of a user
Home-page: https://github.com/wdbm/NM53
Author: Will Breaden Madden
Author-email: wbm@protonmail.ch
License: GPLv3
Platform: UNKNOWN
